[{"gameName":"EJACKPOT","brandName":"EuroJackpot","id":27,"status":"PAYABLE","openTime":1347656640000,"closeTime":1348246800000,"drawTime":1348174800000,"resultsAvailableTime":1348174800000,"addonDraws":[{"gameName":"JOKERI","brandName":"Perjantai-Jokeri","id":1546,"status":"PAYABLE","openTime":1347656400000,"closeTime":1348246800000,"drawTime":1348246800000,"resultsAvailableTime":1348174800000,"results":[{"primary":["0","3","7","9","7","4","7"]}],"prizeTiers":[{"shareCount":0,"shareAmount":0,"totalAmount":0,"name":"7 oikein","id":"1","drawType":"NORMAL"},{"shareCount":0,"shareAmount":0,"totalAmount":0,"name":"6 oikein","id":"2","drawType":"NORMAL"},{"shareCount":9,"shareAmount":144840,"totalAmount":1303560,"name":"5 oikein","id":"3","drawType":"NORMAL"},{"shareCount":256,"shareAmount":5190,"totalAmount":1328640,"name":"4 oikein","id":"4","drawType":"NORMAL"},{"shareCount":2281,"shareAmount":730,"totalAmount":1665130,"name":"3 oikein","id":"5","drawType":"NORMAL"},{"shareCount":12015,"shareAmount":250,"totalAmount":3003750,"name":"2 oikein","id":"6","drawType":"NORMAL"}]}],"results":[{"primary":["18","29","41","44","49"],"secondary":["1","5"]}],"prizeTiers":[{"shareCount":0,"shareAmount":0,"name":"5+2 oikein","id":"1"},{"shareCount":1,"shareAmount":88596000,"name":"5+1 oikein","id":"2"},{"shareCount":0,"shareAmount":0,"name":"5 oikein","id":"3"},{"shareCount":19,"shareAmount":381720,"name":"4+2 oikein","id":"4"},{"shareCount":197,"shareAmount":29140,"name":"4+1 oikein","id":"5"},{"shareCount":261,"shareAmount":13890,"name":"4 oikein","id":"6"},{"shareCount":810,"shareAmount":6340,"name":"3+2 oikein","id":"7"},{"shareCount":10014,"shareAmount":2470,"name":"3+1 oikein","id":"8"},{"shareCount":12625,"shareAmount":1650,"name":"2+2 oikein","id":"9"},{"shareCount":13236,"shareAmount":1640,"name":"3 oikein","id":"10"},{"shareCount":71735,"shareAmount":1010,"name":"1+2 oikein","id":"11"},{"shareCount":149762,"shareAmount":920,"name":"2+1 oikein","id":"12"}]}]