[{"gameName":"EJACKPOT","brandName":"EuroJackpot","id":355,"status":"PAYABLE","openTime":1546038000000,"closeTime":1546624800000,"drawTime":1546631100000,"resultsAvailableTime":1546631100000,"addonDraws":[{"gameName":"JOKERI","brandName":"Perjantai-Jokeri","id":2530,"status":"PAYABLE","openTime":1546038000000,"closeTime":1546624800000,"drawTime":1546631100000,"resultsAvailableTime":1546631100000,"gameRuleSet":{"prizeTierDescriptions":[{"numberOfSelections":1,"numberOfMatchingSelections":1,"multiplier":2,"drawType":"DOUBLING"}]},"results":[{"primary":["3","2","1","8","5","7","8"]}],"prizeTiers":[{"shareCount":0,"shareAmount":0,"totalAmount":0,"name":"7 oikein","id":"1","drawType":"NORMAL"},{"shareCount":2,"shareAmount":2000000,"totalAmount":4000000,"name":"6 oikein","id":"2","drawType":"NORMAL"},{"shareCount":26,"shareAmount":50000,"totalAmount":1300000,"name":"5 oikein","id":"3","drawType":"NORMAL"},{"shareCount":437,"shareAmount":5000,"totalAmount":2185000,"name":"4 oikein","id":"4","drawType":"NORMAL"},{"shareCount":4046,"shareAmount":600,"totalAmount":2427600,"name":"3 oikein","id":"5","drawType":"NORMAL"},{"shareCount":21241,"shareAmount":300,"totalAmount":6372300,"name":"2 oikein","id":"6","drawType":"NORMAL"},{"shareCount":0,"shareAmount":0,"totalAmount":0,"name":"7 oikein","id":"1","multiplier":true,"drawType":"NORMAL"},{"shareCount":1,"shareAmount":4000000,"totalAmount":4000000,"name":"6 oikein","id":"2","multiplier":true,"drawType":"NORMAL"},{"shareCount":13,"shareAmount":100000,"totalAmount":1300000,"name":"5 oikein","id":"3","multiplier":true,"drawType":"NORMAL"},{"shareCount":123,"shareAmount":10000,"totalAmount":1230000,"name":"4 oikein","id":"4","multiplier":true,"drawType":"NORMAL"},{"shareCount":952,"shareAmount":1200,"totalAmount":1142400,"name":"3 oikein","id":"5","multiplier":true,"drawType":"NORMAL"},{"shareCount":3113,"shareAmount":600,"totalAmount":1867800,"name":"2 oikein","id":"6","multiplier":true,"drawType":"NORMAL"}],"jackpots":[{"id":"PRIMARY","amount":100000000}]},{"gameName":"RAFFLE","brandName":"Perjantai-Lomatonni","id":452,"status":"PAYABLE","openTime":1546038000000,"closeTime":1546624800000,"drawTime":1546631100000,"resultsAvailableTime":1546631100000,"gameRuleSet":{"primarySelectionsAllowed":["Amsterdam","Ateena","Bangkok","Barcelona","Berliini","Bryssel","Budapest","Buenos Aires","Cannes","Casablanca","Chicago","Dallas","Delhi","Dubai","Dublin","Firenze","Hampuri","Hanoi","Istanbul","Kairo","Kuala Lumpur","Kööpenhamina","Las Palmas","Lissabon","Lontoo","Los Angeles","Madrid","Malaga","Marrakech","Marseille","Melbourne","Miami","Milano","Monaco","Montreal","Moskova","New York","Nizza","Oslo","Pariisi","Peking","Pietari","Praha","Reykjavik","Riika","Rio de Janeiro","Rooma","San Diego","San Francisco","Santiago","Sao Paulo","Singapore","Sydney","Tallinna","Tokio","Tukholma","Varsova","Venetsia","Wien","Vilna"]},"results":[{"primary":["18"],"secondary":["54"],"drawType":"NORMAL"}],"prizeTiers":[{"shareCount":9,"shareAmount":100000,"name":"Kaupunki ja numero oikein","id":"1"},{"shareCount":1033,"shareAmount":500,"name":"Kaupunki oikein","id":"2"}]}],"results":[{"primary":["3","10","25","32","43"],"secondary":["1","3"]}],"prizeTiers":[{"shareCount":0,"shareAmount":0,"name":"5+2 oikein","id":"1"},{"shareCount":4,"shareAmount":38419010,"name":"5+1 oikein","id":"2"},{"shareCount":5,"shareAmount":10847720,"name":"5+0 oikein","id":"3"},{"shareCount":44,"shareAmount":410890,"name":"4+2 oikein","id":"4"},{"shareCount":788,"shareAmount":20640,"name":"4+1 oikein","id":"5"},{"shareCount":1276,"shareAmount":9910,"name":"4+0 oikein","id":"6"},{"shareCount":1729,"shareAmount":6270,"name":"3+2 oikein","id":"7"},{"shareCount":25530,"shareAmount":2190,"name":"2+2 oikein","id":"8"},{"shareCount":33331,"shareAmount":1620,"name":"3+1 oikein","id":"9"},{"shareCount":54608,"shareAmount":1420,"name":"3+0 oikein","id":"10"},{"shareCount":130755,"shareAmount":1070,"name":"1+2 oikein","id":"11"},{"shareCount":462212,"shareAmount":740,"name":"2+1 oikein","id":"12"}],"jackpots":[{"id":"PRIMARY","amount":1000000000}]}]