[{"gameName":"EJACKPOT","brandName":"EuroJackpot","id":317,"status":"PAYABLE","openTime":1523052000000,"closeTime":1523638800000,"drawTime":1523645100000,"resultsAvailableTime":1523645100000,"addonDraws":[{"gameName":"JOKERI","brandName":"Perjantai-Jokeri","id":2416,"status":"PAYABLE","openTime":1523052000000,"closeTime":1523638800000,"drawTime":1523645100000,"resultsAvailableTime":1523645100000,"gameRuleSet":{"prizeTierDescriptions":[{"numberOfSelections":1,"numberOfMatchingSelections":1,"multiplier":2,"drawType":"DOUBLING"}]},"results":[{"primary":["9","0","5","3","6","0","9"]}],"prizeTiers":[{"shareCount":0,"shareAmount":0,"totalAmount":0,"name":"7 oikein","id":"1","drawType":"NORMAL"},{"shareCount":2,"shareAmount":2000000,"totalAmount":4000000,"name":"6 oikein","id":"2","drawType":"NORMAL"},{"shareCount":31,"shareAmount":50000,"totalAmount":1550000,"name":"5 oikein","id":"3","drawType":"NORMAL"},{"shareCount":447,"shareAmount":5000,"totalAmount":2235000,"name":"4 oikein","id":"4","drawType":"NORMAL"},{"shareCount":4101,"shareAmount":600,"totalAmount":2460600,"name":"3 oikein","id":"5","drawType":"NORMAL"},{"shareCount":21712,"shareAmount":300,"totalAmount":6513600,"name":"2 oikein","id":"6","drawType":"NORMAL"},{"shareCount":0,"shareAmount":0,"totalAmount":0,"name":"7 oikein","id":"1","multiplier":true,"drawType":"NORMAL"},{"shareCount":2,"shareAmount":4000000,"totalAmount":8000000,"name":"6 oikein","id":"2","multiplier":true,"drawType":"NORMAL"},{"shareCount":12,"shareAmount":100000,"totalAmount":1200000,"name":"5 oikein","id":"3","multiplier":true,"drawType":"NORMAL"},{"shareCount":135,"shareAmount":10000,"totalAmount":1350000,"name":"4 oikein","id":"4","multiplier":true,"drawType":"NORMAL"},{"shareCount":973,"shareAmount":1200,"totalAmount":1167600,"name":"3 oikein","id":"5","multiplier":true,"drawType":"NORMAL"},{"shareCount":3404,"shareAmount":600,"totalAmount":2042400,"name":"2 oikein","id":"6","multiplier":true,"drawType":"NORMAL"}],"jackpots":[{"id":"PRIMARY","amount":100000000}]},{"gameName":"RAFFLE","brandName":"Perjantai-Lomatonni","id":338,"status":"PAYABLE","openTime":1523052000000,"closeTime":1523638800000,"drawTime":1523645100000,"resultsAvailableTime":1523645100000,"gameRuleSet":{"primarySelectionsAllowed":["Amsterdam","Ateena","Bangkok","Barcelona","Berliini","Bryssel","Budapest","Buenos Aires","Cannes","Casablanca","Chicago","Dallas","Delhi","Dubai","Dublin","Firenze","Hampuri","Hanoi","Istanbul","Kairo","Kuala Lumpur","Kööpenhamina","Las Palmas","Lissabon","Lontoo","Los Angeles","Madrid","Malaga","Marrakech","Marseille","Melbourne","Miami","Milano","Monaco","Montreal","Moskova","New York","Nizza","Oslo","Pariisi","Peking","Pietari","Praha","Reykjavik","Riika","Rio de Janeiro","Rooma","San Diego","San Francisco","Santiago","Sao Paulo","Singapore","Sydney","Tallinna","Tokio","Tukholma","Varsova","Venetsia","Wien","Vilna"]},"results":[{"primary":["3"],"secondary":["69"],"drawType":"NORMAL"}],"prizeTiers":[{"shareCount":20,"shareAmount":100000,"name":"Kaupunki ja numero oikein","id":"1"},{"shareCount":1192,"shareAmount":500,"name":"Kaupunki oikein","id":"2"}]}],"results":[{"primary":["3","10","21","25","34"],"secondary":["7","10"]}],"prizeTiers":[{"shareCount":0,"shareAmount":0,"name":"5+2 oikein","id":"1"},{"shareCount":5,"shareAmount":32158500,"name":"5+1 oikein","id":"2"},{"shareCount":3,"shareAmount":18916770,"name":"5+0 oikein","id":"3"},{"shareCount":36,"shareAmount":525460,"name":"4+2 oikein","id":"4"},{"shareCount":734,"shareAmount":23190,"name":"4+1 oikein","id":"5"},{"shareCount":1338,"shareAmount":9890,"name":"4+0 oikein","id":"6"},{"shareCount":1562,"shareAmount":7260,"name":"3+2 oikein","id":"7"},{"shareCount":22144,"shareAmount":2640,"name":"2+2 oikein","id":"8"},{"shareCount":31956,"shareAmount":1770,"name":"3+1 oikein","id":"9"},{"shareCount":59936,"shareAmount":1350,"name":"3+0 oikein","id":"10"},{"shareCount":112236,"shareAmount":1310,"name":"1+2 oikein","id":"11"},{"shareCount":451540,"shareAmount":800,"name":"2+1 oikein","id":"12"}],"jackpots":[{"id":"PRIMARY","amount":2400000000},{"id":"SECONDARY","amount":100000000}]}]