{"draws":[{"gameName":"EJACKPOT","brandName":"EuroJackpot","id":"121","status":"PAYABLE","drawTime":1405026000000,"addonDraws":[{"gameName":"JOKERI","brandName":"Perjantai-Jokeri","id":"1828","status":"PAYABLE","drawTime":1405026000000,"gameRuleSet":{"prizeTierDescriptions":[{"numberOfSelections":0,"numberOfMatchingSelections":1,"multiplier":2,"drawType":"DOUBLING"}]},"results":[{"primary":["2","7","4","5","5","4","9"]}],"prizeTiers":[{"shareCount":0,"shareAmount":0,"name":"7 oikein","additionalPrizeTier":false,"multiplier":false,"drawType":"NORMAL"},{"shareCount":2,"shareAmount":628510,"name":"6 oikein","additionalPrizeTier":false,"multiplier":false,"drawType":"NORMAL"},{"shareCount":20,"shareAmount":81040,"name":"5 oikein","additionalPrizeTier":false,"multiplier":false,"drawType":"NORMAL"},{"shareCount":342,"shareAmount":4830,"name":"4 oikein","additionalPrizeTier":false,"multiplier":false,"drawType":"NORMAL"},{"shareCount":2912,"shareAmount":710,"name":"3 oikein","additionalPrizeTier":false,"multiplier":false,"drawType":"NORMAL"},{"shareCount":15950,"shareAmount":250,"name":"2 oikein","additionalPrizeTier":false,"multiplier":false,"drawType":"NORMAL"}],"jackpots":[{"id":"PRIMARY","amount":0}]}],"results":[{"primary":["3","10","16","35","45"],"secondary":["4","6"]}],"prizeTiers":[{"shareCount":0,"shareAmount":0,"name":"5+2 oikein","additionalPrizeTier":false},{"shareCount":2,"shareAmount":20171810,"name":"5+1 oikein","additionalPrizeTier":false},{"shareCount":1,"shareAmount":10489340,"name":"5 oikein","additionalPrizeTier":false},{"shareCount":31,"shareAmount":312330,"name":"4+2 oikein","additionalPrizeTier":false},{"shareCount":298,"shareAmount":25720,"name":"4+1 oikein","additionalPrizeTier":false},{"shareCount":407,"shareAmount":11890,"name":"4 oikein","additionalPrizeTier":false},{"shareCount":1397,"shareAmount":4900,"name":"3+2 oikein","additionalPrizeTier":false},{"shareCount":15021,"shareAmount":2200,"name":"3+1 oikein","additionalPrizeTier":false},{"shareCount":20014,"shareAmount":1410,"name":"2+2 oikein","additionalPrizeTier":false},{"shareCount":20077,"shareAmount":1410,"name":"3 oikein","additionalPrizeTier":false},{"shareCount":104047,"shareAmount":930,"name":"1+2 oikein","additionalPrizeTier":false},{"shareCount":218562,"shareAmount":840,"name":"2+1 oikein","additionalPrizeTier":false}],"jackpots":[{"id":"PRIMARY","amount":-1}]}]}