[{"gameName":"EJACKPOT","brandName":"EuroJackpot","id":39,"status":"PAYABLE","openTime":1354917840000,"closeTime":1355508000000,"drawTime":1355436000000,"resultsAvailableTime":1355436000000,"addonDraws":[{"gameName":"JOKERI","brandName":"Perjantai-Jokeri","id":1582,"status":"PAYABLE","openTime":1354917600000,"closeTime":1355508000000,"drawTime":1355508000000,"resultsAvailableTime":1355436000000,"results":[{"primary":["8","9","1","4","9","9","1"]}],"prizeTiers":[{"shareCount":0,"shareAmount":0,"totalAmount":0,"name":"7 oikein","id":"1","drawType":"NORMAL"},{"shareCount":0,"shareAmount":0,"totalAmount":0,"name":"6 oikein","id":"2","drawType":"NORMAL"},{"shareCount":17,"shareAmount":96340,"totalAmount":1637780,"name":"5 oikein","id":"3","drawType":"NORMAL"},{"shareCount":320,"shareAmount":5220,"totalAmount":1670400,"name":"4 oikein","id":"4","drawType":"NORMAL"},{"shareCount":2839,"shareAmount":740,"totalAmount":2100860,"name":"3 oikein","id":"5","drawType":"NORMAL"},{"shareCount":15706,"shareAmount":250,"totalAmount":3926500,"name":"2 oikein","id":"6","drawType":"NORMAL"}]}],"results":[{"primary":["17","28","31","35","39"],"secondary":["5","8"]}],"prizeTiers":[{"shareCount":0,"shareAmount":0,"name":"5+2 oikein","id":"1"},{"shareCount":5,"shareAmount":6721420,"name":"5+1 oikein","id":"2"},{"shareCount":0,"shareAmount":0,"name":"5 oikein","id":"3"},{"shareCount":18,"shareAmount":448090,"name":"4+2 oikein","id":"4"},{"shareCount":320,"shareAmount":19950,"name":"4+1 oikein","id":"5"},{"shareCount":438,"shareAmount":9200,"name":"4 oikein","id":"6"},{"shareCount":1096,"shareAmount":5210,"name":"3+2 oikein","id":"7"},{"shareCount":13840,"shareAmount":1990,"name":"3+1 oikein","id":"8"},{"shareCount":14587,"shareAmount":1580,"name":"2+2 oikein","id":"9"},{"shareCount":18072,"shareAmount":1330,"name":"3 oikein","id":"10"},{"shareCount":76070,"shareAmount":1060,"name":"1+2 oikein","id":"11"},{"shareCount":186184,"shareAmount":820,"name":"2+1 oikein","id":"12"}]}]