[{"gameName":"EJACKPOT","brandName":"EuroJackpot","id":369,"status":"PAYABLE","openTime":1554501600000,"closeTime":1555088400000,"drawTime":1555094700000,"resultsAvailableTime":1555094700000,"addonDraws":[{"gameName":"JOKERI","brandName":"Perjantai-Jokeri","id":2572,"status":"PAYABLE","openTime":1554501600000,"closeTime":1555088400000,"drawTime":1555094700000,"resultsAvailableTime":1555094700000,"gameRuleSet":{"prizeTierDescriptions":[{"numberOfSelections":1,"numberOfMatchingSelections":1,"multiplier":2,"drawType":"DOUBLING"}]},"results":[{"primary":["8","4","2","8","1","5","8"]}],"prizeTiers":[{"shareCount":0,"shareAmount":0,"totalAmount":0,"name":"7 oikein","id":"1","drawType":"NORMAL"},{"shareCount":2,"shareAmount":2000000,"totalAmount":4000000,"name":"6 oikein","id":"2","drawType":"NORMAL"},{"shareCount":29,"shareAmount":50000,"totalAmount":500000,"name":"5 oikein","id":"3","drawType":"NORMAL"},{"shareCount":501,"shareAmount":5000,"totalAmount":1725000,"name":"4 oikein","id":"4","drawType":"NORMAL"},{"shareCount":4125,"shareAmount":600,"totalAmount":1868400,"name":"3 oikein","id":"5","drawType":"NORMAL"},{"shareCount":22554,"shareAmount":300,"totalAmount":5706300,"name":"2 oikein","id":"6","drawType":"NORMAL"},{"shareCount":0,"shareAmount":0,"totalAmount":0,"name":"7 oikein","id":"1","multiplier":true,"drawType":"NORMAL"},{"shareCount":0,"shareAmount":0,"totalAmount":0,"name":"6 oikein","id":"2","multiplier":true,"drawType":"NORMAL"},{"shareCount":19,"shareAmount":100000,"totalAmount":1900000,"name":"5 oikein","id":"3","multiplier":true,"drawType":"NORMAL"},{"shareCount":156,"shareAmount":10000,"totalAmount":1560000,"name":"4 oikein","id":"4","multiplier":true,"drawType":"NORMAL"},{"shareCount":1011,"shareAmount":1200,"totalAmount":1213200,"name":"3 oikein","id":"5","multiplier":true,"drawType":"NORMAL"},{"shareCount":3533,"shareAmount":600,"totalAmount":2119800,"name":"2 oikein","id":"6","multiplier":true,"drawType":"NORMAL"}],"jackpots":[{"id":"PRIMARY","amount":100000000}]},{"gameName":"RAFFLE","brandName":"Perjantai-Lomatonni","id":494,"status":"PAYABLE","openTime":1554501600000,"closeTime":1555088400000,"drawTime":1555094700000,"resultsAvailableTime":1555094700000,"gameRuleSet":{"primarySelectionsAllowed":["Amsterdam","Ateena","Bangkok","Barcelona","Berliini","Bryssel","Budapest","Buenos Aires","Cannes","Casablanca","Chicago","Dallas","Delhi","Dubai","Dublin","Firenze","Hampuri","Hanoi","Istanbul","Kairo","Kuala Lumpur","Kööpenhamina","Las Palmas","Lissabon","Lontoo","Los Angeles","Madrid","Malaga","Marrakech","Marseille","Melbourne","Miami","Milano","Monaco","Montreal","Moskova","New York","Nizza","Oslo","Pariisi","Peking","Pietari","Praha","Reykjavik","Riika","Rio de Janeiro","Rooma","San Diego","San Francisco","Santiago","Sao Paulo","Singapore","Sydney","Tallinna","Tokio","Tukholma","Varsova","Venetsia","Wien","Vilna"]},"results":[{"primary":["14"],"secondary":["75"],"drawType":"NORMAL"}],"prizeTiers":[{"shareCount":6,"shareAmount":100000,"name":"Kaupunki ja numero oikein","id":"1"},{"shareCount":1115,"shareAmount":500,"name":"Kaupunki oikein","id":"2"}]}],"results":[{"primary":["14","16","21","30","37"],"secondary":["4","8"]}],"prizeTiers":[{"shareCount":0,"shareAmount":0,"name":"5+2 oikein","id":"1"},{"shareCount":4,"shareAmount":48092420,"name":"5+1 oikein","id":"2"},{"shareCount":4,"shareAmount":16973790,"name":"5+0 oikein","id":"3"},{"shareCount":68,"shareAmount":332810,"name":"4+2 oikein","id":"4"},{"shareCount":801,"shareAmount":25420,"name":"4+1 oikein","id":"5"},{"shareCount":1500,"shareAmount":10560,"name":"4+0 oikein","id":"6"},{"shareCount":2767,"shareAmount":4900,"name":"3+2 oikein","id":"7"},{"shareCount":40898,"shareAmount":1750,"name":"2+2 oikein","id":"8"},{"shareCount":37823,"shareAmount":1750,"name":"3+1 oikein","id":"9"},{"shareCount":62912,"shareAmount":1540,"name":"3+0 oikein","id":"10"},{"shareCount":218799,"shareAmount":800,"name":"1+2 oikein","id":"11"},{"shareCount":539495,"shareAmount":800,"name":"2+1 oikein","id":"12"}],"jackpots":[{"id":"PRIMARY","amount":3900000000},{"id":"SECONDARY","amount":100000000}]}]