{"draws":[{"gameName":"EJACKPOT","brandName":"EuroJackpot","id":"211","status":"PAYABLE","drawTime":1459458000000,"addonDraws":[{"gameName":"JOKERI","brandName":"Perjantai-Jokeri","id":"2098","status":"PAYABLE","drawTime":1459458000000,"gameRuleSet":{"prizeTierDescriptions":[{"numberOfSelections":1,"numberOfMatchingSelections":1,"multiplier":2,"drawType":"DOUBLING"}]},"results":[{"primary":["8","7","8","5","7","4","0"]}],"prizeTiers":[{"shareCount":0,"shareAmount":0,"name":"7 oikein","additionalPrizeTier":false,"multiplier":false,"drawType":"NORMAL"},{"shareCount":1,"shareAmount":2000000,"name":"6 oikein","additionalPrizeTier":false,"multiplier":false,"drawType":"NORMAL"},{"shareCount":26,"shareAmount":50000,"name":"5 oikein","additionalPrizeTier":false,"multiplier":false,"drawType":"NORMAL"},{"shareCount":488,"shareAmount":5000,"name":"4 oikein","additionalPrizeTier":false,"multiplier":false,"drawType":"NORMAL"},{"shareCount":4135,"shareAmount":600,"name":"3 oikein","additionalPrizeTier":false,"multiplier":false,"drawType":"NORMAL"},{"shareCount":23135,"shareAmount":300,"name":"2 oikein","additionalPrizeTier":false,"multiplier":false,"drawType":"NORMAL"},{"shareCount":0,"shareAmount":0,"name":"7 oikein","additionalPrizeTier":false,"multiplier":true,"drawType":"NORMAL"},{"shareCount":0,"shareAmount":0,"name":"6 oikein","additionalPrizeTier":false,"multiplier":true,"drawType":"NORMAL"},{"shareCount":10,"shareAmount":100000,"name":"5 oikein","additionalPrizeTier":false,"multiplier":true,"drawType":"NORMAL"},{"shareCount":155,"shareAmount":10000,"name":"4 oikein","additionalPrizeTier":false,"multiplier":true,"drawType":"NORMAL"},{"shareCount":861,"shareAmount":1200,"name":"3 oikein","additionalPrizeTier":false,"multiplier":true,"drawType":"NORMAL"},{"shareCount":3324,"shareAmount":600,"name":"2 oikein","additionalPrizeTier":false,"multiplier":true,"drawType":"NORMAL"}],"jackpots":[{"id":"PRIMARY","amount":0}]}],"results":[{"primary":["6","12","21","40","49"],"secondary":["8","10"]}],"prizeTiers":[{"shareCount":0,"shareAmount":0,"name":"5+2 oikein","additionalPrizeTier":false},{"shareCount":1,"shareAmount":114782130,"name":"5+1 oikein","additionalPrizeTier":false},{"shareCount":2,"shareAmount":20255670,"name":"5 oikein","additionalPrizeTier":false},{"shareCount":17,"shareAmount":794340,"name":"4+2 oikein","additionalPrizeTier":false},{"shareCount":413,"shareAmount":29420,"name":"4+1 oikein","additionalPrizeTier":false},{"shareCount":850,"shareAmount":11120,"name":"4 oikein","additionalPrizeTier":false},{"shareCount":837,"shareAmount":9680,"name":"3+2 oikein","additionalPrizeTier":false},{"shareCount":12865,"shareAmount":3250,"name":"2+2 oikein","additionalPrizeTier":false},{"shareCount":18461,"shareAmount":2190,"name":"3+1 oikein","additionalPrizeTier":false},{"shareCount":36863,"shareAmount":1570,"name":"3 oikein","additionalPrizeTier":false},{"shareCount":69149,"shareAmount":1520,"name":"1+2 oikein","additionalPrizeTier":false},{"shareCount":280055,"shareAmount":920,"name":"2+1 oikein","additionalPrizeTier":false}],"jackpots":[{"id":"PRIMARY","amount":-1}]}]}