{"draws":[{"gameName":"LOTTO","brandName":"Lotto","id":"1281","status":"PAYABLE","drawTime":1406926800000,"addonDraws":[{"gameName":"JOKERI","brandName":"Lauantai-Jokeri","id":"1838","status":"PAYABLE","drawTime":1406926800000,"gameRuleSet":{"prizeTierDescriptions":[{"numberOfSelections":0,"numberOfMatchingSelections":1,"multiplier":2,"drawType":"DOUBLING"}]},"results":[{"primary":["4","8","9","0","4","6","0"]}],"prizeTiers":[{"shareCount":0,"shareAmount":0,"name":"7 oikein","additionalPrizeTier":false,"multiplier":false,"drawType":"NORMAL"},{"shareCount":3,"shareAmount":2888940,"name":"6 oikein","additionalPrizeTier":false,"multiplier":false,"drawType":"NORMAL"},{"shareCount":80,"shareAmount":88910,"name":"5 oikein","additionalPrizeTier":false,"multiplier":false,"drawType":"NORMAL"},{"shareCount":1361,"shareAmount":5330,"name":"4 oikein","additionalPrizeTier":false,"multiplier":false,"drawType":"NORMAL"},{"shareCount":12297,"shareAmount":740,"name":"3 oikein","additionalPrizeTier":false,"multiplier":false,"drawType":"NORMAL"},{"shareCount":66840,"shareAmount":250,"name":"2 oikein","additionalPrizeTier":false,"multiplier":false,"drawType":"NORMAL"}],"jackpots":[{"id":"PRIMARY","amount":0}]}],"results":[{"primary":["3","15","20","21","29","30","33"],"secondary":["6","10"],"multiplier":15,"drawType":"NORMAL"}],"prizeTiers":[{"shareCount":1,"shareAmount":130000000,"name":"7 oikein","additionalPrizeTier":false,"multiplier":false,"drawType":"NORMAL"},{"shareCount":7,"shareAmount":4521780,"name":"6+1 oikein","additionalPrizeTier":false,"multiplier":false,"drawType":"NORMAL"},{"shareCount":98,"shareAmount":196590,"name":"6 oikein","additionalPrizeTier":false,"multiplier":false,"drawType":"NORMAL"},{"shareCount":5064,"shareAmount":4610,"name":"5 oikein","additionalPrizeTier":false,"multiplier":false,"drawType":"NORMAL"},{"shareCount":83880,"shareAmount":1000,"name":"4 oikein","additionalPrizeTier":false,"multiplier":false,"drawType":"NORMAL"},{"shareCount":0,"shareAmount":0,"name":"7 oikein","additionalPrizeTier":false,"multiplier":true,"drawType":"NORMAL"},{"shareCount":1,"shareAmount":9043560,"name":"6+1 oikein","additionalPrizeTier":false,"multiplier":true,"drawType":"NORMAL"},{"shareCount":31,"shareAmount":393180,"name":"6 oikein","additionalPrizeTier":false,"multiplier":true,"drawType":"NORMAL"},{"shareCount":1076,"shareAmount":9220,"name":"5 oikein","additionalPrizeTier":false,"multiplier":true,"drawType":"NORMAL"},{"shareCount":14834,"shareAmount":2000,"name":"4 oikein","additionalPrizeTier":false,"multiplier":true,"drawType":"NORMAL"}],"jackpots":[{"id":"PRIMARY","amount":-1}]}]}