{"draws":[{"gameName":"LOTTO","brandName":"Lotto","id":"1060","status":"PAYABLE","drawTime":1273266000000,"addonDraws":[{"gameName":"JOKERI","brandName":"Lauantai-Jokeri","id":"1271","status":"PAYABLE","drawTime":1273266000000,"gameRuleSet":{"prizeTierDescriptions":[{"numberOfSelections":0,"numberOfMatchingSelections":1,"multiplier":2,"drawType":"DOUBLING"}]},"results":[{"primary":["7","1","6","3","2","6","6"]}],"prizeTiers":[{"shareCount":0,"shareAmount":0,"name":"7 oikein","additionalPrizeTier":false,"multiplier":false,"drawType":"NORMAL"},{"shareCount":4,"shareAmount":1698630,"name":"6 oikein","additionalPrizeTier":false,"multiplier":false,"drawType":"NORMAL"},{"shareCount":115,"shareAmount":76180,"name":"5 oikein","additionalPrizeTier":false,"multiplier":false,"drawType":"NORMAL"},{"shareCount":1666,"shareAmount":5360,"name":"4 oikein","additionalPrizeTier":false,"multiplier":false,"drawType":"NORMAL"},{"shareCount":15360,"shareAmount":730,"name":"3 oikein","additionalPrizeTier":false,"multiplier":false,"drawType":"NORMAL"},{"shareCount":82824,"shareAmount":250,"name":"2 oikein","additionalPrizeTier":false,"multiplier":false,"drawType":"NORMAL"}],"jackpots":[{"id":"PRIMARY","amount":0}]}],"results":[{"primary":["2","10","14","15","16","20","36"],"secondary":["21","29","39"],"tertiary":[],"drawType":"NORMAL"}],"prizeTiers":[{"shareCount":1,"shareAmount":220000000,"name":"7 oikein","additionalPrizeTier":false,"multiplier":false,"drawType":"NORMAL"},{"shareCount":12,"shareAmount":1730720,"name":"6+1 oikein","additionalPrizeTier":false,"multiplier":false,"drawType":"NORMAL"},{"shareCount":117,"shareAmount":188370,"name":"6 oikein","additionalPrizeTier":false,"multiplier":false,"drawType":"NORMAL"},{"shareCount":5965,"shareAmount":5610,"name":"5 oikein","additionalPrizeTier":false,"multiplier":false,"drawType":"NORMAL"},{"shareCount":113894,"shareAmount":1220,"name":"4 oikein","additionalPrizeTier":false,"multiplier":false,"drawType":"NORMAL"},{"shareCount":10,"shareAmount":524460,"name":"4+3 oikein","additionalPrizeTier":true,"multiplier":false,"drawType":"NORMAL"},{"shareCount":964,"shareAmount":4640,"name":"4+2 oikein","additionalPrizeTier":true,"multiplier":false,"drawType":"NORMAL"},{"shareCount":13923,"shareAmount":560,"name":"4+1 oikein","additionalPrizeTier":true,"multiplier":false,"drawType":"NORMAL"},{"shareCount":348,"shareAmount":14450,"name":"3+3 oikein","additionalPrizeTier":true,"multiplier":false,"drawType":"NORMAL"},{"shareCount":13625,"shareAmount":570,"name":"3+2 oikein","additionalPrizeTier":true,"multiplier":false,"drawType":"NORMAL"},{"shareCount":128418,"shareAmount":100,"name":"3+1 oikein","additionalPrizeTier":true,"multiplier":false,"drawType":"NORMAL"}],"jackpots":[{"id":"PRIMARY","amount":-1}]}]}